starcrusher2025_games/__init__.py
starcrusher2025_games/game.py
starcrusher2025_games/configs/GameObject.py
starcrusher2025_games/configs/__init__.py
starcrusher2025_games/configs/ingame_menu.py
starcrusher2025_games/configs/menu.py
starcrusher2025_games/configs/menu_config.py
starcrusher2025_games/configs/player.py
starcrusher2025_games/configs/window.py
starcrusher2025_games/update/__init__.py
starcrusher2025_games/update/requests.py
starcrusher2025_games-1.1.5.dist-info/LICENSE.md
starcrusher2025_games-1.1.5.dist-info/METADATA
starcrusher2025_games-1.1.5.dist-info/WHEEL
starcrusher2025_games-1.1.5.dist-info/entry_points.txt
starcrusher2025_games-1.1.5.dist-info/top_level.txt
starcrusher2025_games-1.1.5.dist-info/RECORD
