Metadata-Version: 2.1
Name: starcrusher2025_games
Version: 1.1.5
Summary: A easy to use game engine.
Home-page: https://github.com/starcrusher2025/2025_games
Author: starcrusher2025
License: MIT
License-File: LICENSE.md
Requires-Dist: pygame
Requires-Dist: requests
